{"cameraMode":{"drawMode":0,"name":"Shaded","section":"Shading Mode"},"sceneLighting":false,"audioPlay":false,"sceneViewState":{"m_AlwaysRefresh":true,"showFog":true,"showSkybox":false,"showFlares":true,"showImageEffects":true,"showParticleSystems":true,"showVisualEffectGraphs":true,"m_FxEnabled":false},"in2DMode":false,"pivot":{"x":-98.07368469238281,"y":21.141803741455079,"z":-511.7800598144531},"rotation":{"x":-0.02826620079576969,"y":0.9719840288162231,"z":-0.17321333289146424,"w":-0.15706849098205567},"size":20.532461166381837,"orthographic":false}